advanced_database_replace/__init__.py
advanced_database_replace/database.py
advanced_database_replace/database_credentials.py
advanced_database_replace/database_replace.py
advanced_database_replace/replacer.py
advanced_database_replace-1.0.0.dist-info/LICENSE.txt
advanced_database_replace-1.0.0.dist-info/METADATA
advanced_database_replace-1.0.0.dist-info/WHEEL
advanced_database_replace-1.0.0.dist-info/top_level.txt
advanced_database_replace-1.0.0.dist-info/RECORD
