Metadata-Version: 2.1
Name: advanced-database-replace
Version: 1.0.0
Summary: Utility package which runs an advanced search&replace on a mysql database.
Home-page: https://github.com/laimonassutkus/AdvancedDatabaseReplace
Author: Laimonas Sutkus
Author-email: laimonas.sutkus@gmail.com
License: UNKNOWN
Keywords: Wordpress Database Replace Search Replace
Platform: UNKNOWN
Classifier: Programming Language :: Python :: 3
Classifier: Programming Language :: Python :: 3.5
Classifier: Programming Language :: Python :: 3.6
Classifier: Programming Language :: Python :: 3.7
Classifier: Operating System :: POSIX :: Linux
Requires-Dist: phpserialize (<2.0,>=1.3)
Requires-Dist: PyMySQL (<1.0.0,>=0.9.3)
